CHANGELOG.md
LICENSE
camelcalc/__init__.py
camelcalc/camelcalc.py
camelcalc/camelup.py
camelcalc/linkedlist.py
camelcalc/play.py
camelcalc/utils.py
camelcalc-0.1.1.dist-info/entry_points.txt
camelcalc-0.1.1.dist-info/LICENSE
camelcalc-0.1.1.dist-info/WHEEL
camelcalc-0.1.1.dist-info/METADATA
camelcalc-0.1.1.dist-info/RECORD
