Metadata-Version: 2.1
Name: camelcalc
Version: 0.1.1
Summary: A Camel Up simulator and optimizer
Home-page: https://github.com/ArmaanT/camelcalc
License: MIT
Author: Armaan Tobaccowalla
Author-email: armaan@tobaccowalla.com
Requires-Python: >=3.8,<4.0
Classifier: License :: OSI Approved :: MIT License
Classifier: Programming Language :: Python :: 3
Classifier: Programming Language :: Python :: 3.8
Classifier: Programming Language :: Python :: 3.9
Project-URL: Repository, https://github.com/ArmaanT/camelcalc
